d_flip_flop/d_flip_flop.v
// ----D FLIP FLOP MODULE--------------------------------------
// Storage of a one bit of data
// Input clk -  Clock input
// Input data -  Data bit recieved
// Output Q - Sotred output
// Output not_Q - Inverted stored output

// Written by Asanka Sovis (08/09/2022)
// Based on the 8-bit Computer series by Ben Eater
// ------------------------------------------------------------

module d_flip_flop (clk, data, Q, not_Q);

    input clk, data;
    output Q, not_Q;

    wire feedback1, feedback2;
    reg a;

    assign feedback1 = ~((~(a)) || feedback2);
    assign feedback2 = ~((a) || feedback1);

    always @(posedge clk) 
    begin
        a <= data;
    end 

    assign Q = feedback1;
    assign not_Q = feedback2;

endmodule

clock/clock.v
// ----CLOCK MODULE--------------------------------------------
// Outputs the clock pulse needed to drive the computer
// Input apulse -  Astable pulse from a clock source
// Input select -  Select line (Select astable pulse if high and
//                          manual pulse when low)
// Input mpulse - Manual pulse that a user can send
// Input hlt - Overrides all other inputs and halt the clock
// Output clk - The returned clock pulse

// Written by Asanka Sovis (04/09/2022)
// Based on the 8-bit Computer series by Ben Eater
// ------------------------------------------------------------

module clock (apulse, select, mpulse, hlt, clk);

    input apulse, select, mpulse, hlt;
    output clk;

    assign clk = ((apulse && select) || (mpulse && ~select)) && ~hlt;

endmodule

clock/test_clock.v
`timescale 1ns/1ns
`include "../clock/clock.v"

module test_clock (clk);

    reg apulse, select, mpulse, hlt;
    output clk;

    initial apulse = 1;

    initial select = 1; // Selecting astable pulse
    initial mpulse = 0; // Resetting manual pulse
    initial hlt = 0; // Resetting halt signal

    clock test(apulse, select, mpulse, hlt, clk);

    always begin
        #2 apulse = ~apulse;
        #2 apulse = ~apulse;
    end

endmodule

d_flip_flop/d_flip_flop_tb.v
// ----TESTBENCH FOR D FLIP FLOP--------------------------------

// Written by Asanka Sovis (08/09/2022)
// Based on the 8-bit Computer series by Ben Eater
// ------------------------------------------------------------

`timescale 1ns/1ns
`include "d_flip_flop.v"
`include "../clock/test_clock.v"

module d_flip_flop_tb;

    reg data;
    wire clk, Q, not_Q;

    test_clock clock(clk);
    d_flip_flop uut(clk, data, Q, not_Q);

    initial begin
        $dumpfile("d_flip_flop_tb.vcd");
        $dumpvars(0, d_flip_flop_tb);

        data <= 0; // Data is low
        // Must set Q to low

        #10 data <= 1; // Data goes high
        // Must set Q to high on next pulse

        data <= 0; // Data goes low
        // Must not change the Q value

        data <= 1; // Data goes high
        // Must not change the Q value

        #10 $finish;
        $display("Test Complete");
    end

endmodule

d_flip_flop/d_flip_flop_tb.vcd
$date
	Sun Sep 25 12:18:15 2022
$end
$version
	Icarus Verilog
$end
$timescale
	1ns
$end
$scope module d_flip_flop_tb $end
$var wire 1 ! not_Q $end
$var wire 1 " clk $end
$var wire 1 # Q $end
$var reg 1 $ data $end
$scope module clock $end
$var wire 1 " clk $end
$var reg 1 % apulse $end
$var reg 1 & hlt $end
$var reg 1 ' mpulse $end
$var reg 1 ( select $end
$scope module test $end
$var wire 1 % apulse $end
$var wire 1 " clk $end
$var wire 1 & hlt $end
$var wire 1 ' mpulse $end
$var wire 1 ( select $end
$upscope $end
$upscope $end
$scope module uut $end
$var wire 1 # Q $end
$var wire 1 " clk $end
$var wire 1 $ data $end
$var wire 1 ) feedback1 $end
$var wire 1 * feedback2 $end
$var wire 1 ! not_Q $end
$var reg 1 + a $end
$upscope $end
$upscope $end
$enddefinitions $end
$comment Show the parameter values. $end
$dumpall
$end
#0
$dumpvars
x+
x*
x)
1(
0'
0&
1%
0$
x#
1"
x!
$end
#2
0"
0%
#4
1!
1*
0#
0)
0+
1"
1%
#6
0"
0%
#8
1"
1%
#10
1$
0"
0%
#12
1#
1)
0!
0*
1+
1"
1%
#14
0"
0%
#16
1"
1%
#18
0"
0%
#20
1"
1%
