clock/clock.v
// ----CLOCK MODULE--------------------------------------------
// Outputs the clock pulse needed to drive the computer
// Input apulse -  Astable pulse from a clock source
// Input select -  Select line (Select astable pulse if high and
//                          manual pulse when low)
// Input mpulse - Manual pulse that a user can send
// Input hlt - Overrides all other inputs and halt the clock
// Output clk - The returned clock pulse

// Written by Asanka Sovis (04/09/2022)
// Based on the 8-bit Computer series by Ben Eater
// ------------------------------------------------------------

module clock (apulse, select, mpulse, hlt, clk);

    input apulse, select, mpulse, hlt;
    output clk;

    assign clk = ((apulse && select) || (mpulse && ~select)) && ~hlt;

endmodule

clock/test_clock.v
`timescale 1ns/1ns
`include "../clock/clock.v"

module test_clock (clk);

    reg apulse, select, mpulse, hlt;
    output clk;

    initial apulse = 1;

    initial select = 1; // Selecting astable pulse
    initial mpulse = 0; // Resetting manual pulse
    initial hlt = 0; // Resetting halt signal

    clock test(apulse, select, mpulse, hlt, clk);

    always begin
        #2 apulse = ~apulse;
        #2 apulse = ~apulse;
    end

endmodule

clock/test_clock_tb.v
`timescale 1ns/1ns
`include "test_clock.v"

module test_clock_tb;

    wire clk;

    test_clock uut(clk);

    initial begin
        $dumpfile("test_clock_tb.vcd");
        $dumpvars(0, test_clock_tb);

        #10 $finish;

        $display("Test Complete");
    end

endmodule

clock/test_clock_tb.vcd
$date
	Sat Sep 24 21:42:29 2022
$end
$version
	Icarus Verilog
$end
$timescale
	1ns
$end
$scope module test_clock_tb $end
$var wire 1 ! clk $end
$scope module uut $end
$var wire 1 ! clk $end
$var reg 1 " apulse $end
$var reg 1 # hlt $end
$var reg 1 $ mpulse $end
$var reg 1 % select $end
$scope module test $end
$var wire 1 " apulse $end
$var wire 1 ! clk $end
$var wire 1 # hlt $end
$var wire 1 $ mpulse $end
$var wire 1 % select $end
$upscope $end
$upscope $end
$upscope $end
$enddefinitions $end
$comment Show the parameter values. $end
$dumpall
$end
#0
$dumpvars
1%
0$
0#
1"
1!
$end
#1
0!
0"
#2
1!
1"
#3
0!
0"
#4
1!
1"
#5
0!
0"
#6
1!
1"
#7
0!
0"
#8
1!
1"
#9
0!
0"
#10
1!
1"
