bit_register/bit_register.v
// ----BIT REGISTER MODULE-------------------------------------
// One bit register to store a bit
// Input clk -  Clock input
// Input input_enable -  Enable the input
// Input output_enable - Enable the output
// Input data - Input data
// Output out - Output data

// Written by Asanka Sovis (25/09/2022)
// Based on the 8-bit Computer series by Ben Eater
// ------------------------------------------------------------

`include "../d_flip_flop/d_flip_flop.v"

module bit_register(clk, input_enable, output_enable, data, out);

    input clk, input_enable, output_enable, data;
    output out;

    wire not_out;
    wire buf_out;

    wire mem_data;

    assign mem_data = (buf_out && ~input_enable) || (input_enable && data);

    d_flip_flop flip_memory (clk, mem_data, buf_out, not_out);

    buffer buf_memory (buf_out, output_enable, out);

endmodule

// ----BUFFER MODULE-------------------------------------------
// Buffer to hold data without output
// Input data - Input data
// Input enable - Enable the output
// Output out - Output data

// Written by Asanka Sovis (24/09/2022)
// Based on the 8-bit Computer series by Ben Eater
// ------------------------------------------------------------

module buffer(data, enable, out);

    input data, enable;
    output reg out;

    always @* begin
        if (enable == 1) begin
            out <= data;
        end
        else begin
            out <= 1'bZ;
        end
    end

endmodule

d_flip_flop/d_flip_flop.v
// ----D FLIP FLOP MODULE--------------------------------------
// Storage of a one bit of data
// Input clk -  Clock input
// Input data -  Data bit recieved
// Output Q - Sotred output
// Output not_Q - Inverted stored output

// Written by Asanka Sovis (08/09/2022)
// Based on the 8-bit Computer series by Ben Eater
// ------------------------------------------------------------

module d_flip_flop (clk, data, Q, not_Q);

    input clk, data;
    output Q, not_Q;

    wire feedback1, feedback2;
    reg a;

    assign feedback1 = ~((~(a)) || feedback2);
    assign feedback2 = ~((a) || feedback1);

    always @(posedge clk) 
    begin
        a <= data;
    end 

    assign Q = feedback1;
    assign not_Q = feedback2;

endmodule

clock/clock.v
// ----CLOCK MODULE--------------------------------------------
// Outputs the clock pulse needed to drive the computer
// Input apulse -  Astable pulse from a clock source
// Input select -  Select line (Select astable pulse if high and
//                          manual pulse when low)
// Input mpulse - Manual pulse that a user can send
// Input hlt - Overrides all other inputs and halt the clock
// Output clk - The returned clock pulse

// Written by Asanka Sovis (04/09/2022)
// Based on the 8-bit Computer series by Ben Eater
// ------------------------------------------------------------

module clock (apulse, select, mpulse, hlt, clk);

    input apulse, select, mpulse, hlt;
    output clk;

    assign clk = ((apulse && select) || (mpulse && ~select)) && ~hlt;

endmodule

clock/test_clock.v
`timescale 1ns/1ns
`include "../clock/clock.v"

module test_clock (clk);

    reg apulse, select, mpulse, hlt;
    output clk;

    initial apulse = 1;

    initial select = 1; // Selecting astable pulse
    initial mpulse = 0; // Resetting manual pulse
    initial hlt = 0; // Resetting halt signal

    clock test(apulse, select, mpulse, hlt, clk);

    always begin
        #2 apulse = ~apulse;
        #2 apulse = ~apulse;
    end

endmodule

bit_register/bit_register_tb.v
// ----TESTBENCH FOR ONE BIT REGISTER--------------------------

// Written by Asanka Sovis (25/09/2022)
// Based on the 8-bit Computer series by Ben Eater
// ------------------------------------------------------------

`timescale 1ns/1ns
`include "bit_register.v"
`include "../clock/test_clock.v"

module bit_register_tb;

    reg input_enable, output_enable, data;
    wire out, clk;

    test_clock clock(clk);

    bit_register uut(clk, input_enable, output_enable, data, out);

    initial begin
        $dumpfile("bit_register_tb.vcd");
        $dumpvars(0, bit_register_tb);

        input_enable <= 0;
        output_enable <= 0;
        data <= 0;

        #2 input_enable <= 1; // Enable input
        data <= 1; // Set data high
        // On next clock pulse, the memory should go hgih

        #2 input_enable <= 0; // Disable input
        data <= 0; // Set data low
        // Memory must stay high
        
        #3 output_enable <= 1;
        #1 output_enable <= 0; // Enable output for one clock pulse
        // Output must show high

        #2 input_enable <= 1;
        #2 input_enable <= 0; // Enable input for one clock pulse
        // Memory must switch to low
        
        #2 output_enable <= 1;
        #1 output_enable <= 0; // Enable output for one clock pulse
        // Output must show low

        #10 $finish;
        $display("Test Complete");
    end

endmodule

bit_register/bit_register_tb.vcd
$date
	Sun Sep 25 12:28:57 2022
$end
$version
	Icarus Verilog
$end
$timescale
	1ns
$end
$scope module bit_register_tb $end
$var wire 1 ! out $end
$var wire 1 " clk $end
$var reg 1 # data $end
$var reg 1 $ input_enable $end
$var reg 1 % output_enable $end
$scope module clock $end
$var wire 1 " clk $end
$var reg 1 & apulse $end
$var reg 1 ' hlt $end
$var reg 1 ( mpulse $end
$var reg 1 ) select $end
$scope module test $end
$var wire 1 & apulse $end
$var wire 1 " clk $end
$var wire 1 ' hlt $end
$var wire 1 ( mpulse $end
$var wire 1 ) select $end
$upscope $end
$upscope $end
$scope module uut $end
$var wire 1 " clk $end
$var wire 1 # data $end
$var wire 1 $ input_enable $end
$var wire 1 * mem_data $end
$var wire 1 % output_enable $end
$var wire 1 ! out $end
$var wire 1 + not_out $end
$var wire 1 , buf_out $end
$scope module buf_memory $end
$var wire 1 % enable $end
$var wire 1 , data $end
$var reg 1 ! out $end
$upscope $end
$scope module flip_memory $end
$var wire 1 , Q $end
$var wire 1 " clk $end
$var wire 1 * data $end
$var wire 1 - feedback1 $end
$var wire 1 . feedback2 $end
$var wire 1 + not_Q $end
$var reg 1 / a $end
$upscope $end
$upscope $end
$upscope $end
$enddefinitions $end
$comment Show the parameter values. $end
$dumpall
$end
#0
$dumpvars
x/
x.
x-
x,
x+
x*
1)
0(
0'
1&
0%
0$
0#
1"
z!
$end
#2
1*
1#
1$
0"
0&
#4
1,
1-
0+
0.
1*
1/
0#
0$
1"
1&
#6
0"
0&
#7
1!
1%
#8
z!
0%
1"
1&
#10
0*
1$
0"
0&
#12
1+
1.
0,
0-
0*
0/
0$
1"
1&
#14
0!
1%
0"
0&
#15
z!
0%
#16
1"
1&
#18
0"
0&
#20
1"
1&
#22
0"
0&
#24
1"
1&
